mythos_api-0.0.3-py3.7-nspkg.pth
mythos/api/LICENSE
mythos/api/README.md
mythos/api/__init__.py
mythos/api/__version__.py
mythos_api-0.0.3.dist-info/LICENSE
mythos_api-0.0.3.dist-info/METADATA
mythos_api-0.0.3.dist-info/WHEEL
mythos_api-0.0.3.dist-info/entry_points.txt
mythos_api-0.0.3.dist-info/namespace_packages.txt
mythos_api-0.0.3.dist-info/top_level.txt
mythos_api-0.0.3.dist-info/RECORD
